[{"__type__":"cc.SpriteFrame","content":{"name":"1154","texture":"0fAmK8znJEboyQHpj8C1vF","rect":[0,600,100,100],"offset":[0,0],"originalSize":[100,100],"capInsets":[0,0,0,0]}},{"__type__":"cc.SpriteFrame","content":{"name":"1895","texture":"0fAmK8znJEboyQHpj8C1vF","rect":[500,200,100,100],"offset":[0,0],"originalSize":[100,100],"capInsets":[0,0,0,0]}},{"__type__":"cc.SpriteFrame","content":{"name":"288","texture":"0fAmK8znJEboyQHpj8C1vF","rect":[900,600,100,100],"offset":[0,0],"originalSize":[100,100],"capInsets":[0,0,0,0]}},{"__type__":"cc.SpriteFrame","content":{"name":"1922","texture":"0fAmK8znJEboyQHpj8C1vF","rect":[400,800,100,100],"offset":[0,0],"originalSize":[100,100],"capInsets":[0,0,0,0]}},{"__type__":"cc.SpriteFrame","content":{"name":"296","texture":"0fAmK8znJEboyQHpj8C1vF","rect":[800,900,100,100],"offset":[0,0],"originalSize":[100,100],"capInsets":[0,0,0,0]}},{"__type__":"cc.SpriteFrame","content":{"name":"1158","texture":"0fAmK8znJEboyQHpj8C1vF","rect":[100,0,100,100],"offset":[0,0],"originalSize":[100,100],"capInsets":[0,0,0,0]}},{"__type__":"cc.SpriteFrame","content":{"name":"1366","texture":"0fAmK8znJEboyQHpj8C1vF","rect":[100,900,100,100],"offset":[0,0],"originalSize":[100,100],"capInsets":[0,0,0,0]}},{"__type__":"cc.SpriteFrame","content":{"name":"1062","texture":"0fAmK8znJEboyQHpj8C1vF","rect":[0,200,100,100],"offset":[0,0],"originalSize":[100,100],"capInsets":[0,0,0,0]}},{"__type__":"cc.SpriteFrame","content":{"name":"1785","texture":"0fAmK8znJEboyQHpj8C1vF","rect":[200,700,100,100],"offset":[0,0],"originalSize":[100,100],"capInsets":[0,0,0,0]}},{"__type__":"cc.SpriteFrame","content":{"name":"1156","texture":"0fAmK8znJEboyQHpj8C1vF","rect":[0,800,100,100],"offset":[0,0],"originalSize":[100,100],"capInsets":[0,0,0,0]}},{"__type__":"cc.SpriteFrame","content":{"name":"2220","texture":"0fAmK8znJEboyQHpj8C1vF","rect":[500,900,100,100],"offset":[0,0],"originalSize":[100,100],"capInsets":[0,0,0,0]}},{"__type__":"cc.SpriteFrame","content":{"name":"295","texture":"0fAmK8znJEboyQHpj8C1vF","rect":[800,800,100,100],"offset":[0,0],"originalSize":[100,100],"capInsets":[0,0,0,0]}},{"__type__":"cc.SpriteFrame","content":{"name":"1891","texture":"0fAmK8znJEboyQHpj8C1vF","rect":[200,800,100,100],"offset":[0,0],"originalSize":[100,100],"capInsets":[0,0,0,0]}},{"__type__":"cc.SpriteFrame","content":{"name":"1901","texture":"0fAmK8znJEboyQHpj8C1vF","rect":[300,400,100,100],"offset":[0,0],"originalSize":[100,100],"capInsets":[0,0,0,0]}},{"__type__":"cc.SpriteFrame","content":{"name":"1508","texture":"0fAmK8znJEboyQHpj8C1vF","rect":[300,100,100,100],"offset":[0,0],"originalSize":[100,100],"capInsets":[0,0,0,0]}},{"__type__":"cc.SpriteFrame","content":{"name":"1028","texture":"0fAmK8znJEboyQHpj8C1vF","rect":[0,0,100,100],"offset":[0,0],"originalSize":[100,100],"capInsets":[0,0,0,0]}},{"__type__":"cc.SpriteFrame","content":{"name":"1029","texture":"0fAmK8znJEboyQHpj8C1vF","rect":[0,100,100,100],"offset":[0,0],"originalSize":[100,100],"capInsets":[0,0,0,0]}},{"__type__":"cc.SpriteFrame","content":{"name":"1571","texture":"0fAmK8znJEboyQHpj8C1vF","rect":[600,100,100,100],"offset":[0,0],"originalSize":[100,100],"capInsets":[0,0,0,0]}},{"__type__":"cc.SpriteFrame","content":{"name":"1159","texture":"0fAmK8znJEboyQHpj8C1vF","rect":[200,0,100,100],"offset":[0,0],"originalSize":[100,100],"capInsets":[0,0,0,0]}},{"__type__":"cc.SpriteFrame","content":{"name":"1738","texture":"0fAmK8znJEboyQHpj8C1vF","rect":[200,500,100,100],"offset":[0,0],"originalSize":[100,100],"capInsets":[0,0,0,0]}},{"__type__":"cc.SpriteFrame","content":{"name":"1916","texture":"0fAmK8znJEboyQHpj8C1vF","rect":[400,500,100,100],"offset":[0,0],"originalSize":[100,100],"capInsets":[0,0,0,0]}},{"__type__":"cc.SpriteFrame","content":{"name":"278","texture":"0fAmK8znJEboyQHpj8C1vF","rect":[700,500,100,100],"offset":[0,0],"originalSize":[100,100],"capInsets":[0,0,0,0]}},{"__type__":"cc.SpriteFrame","content":{"name":"1161","texture":"0fAmK8znJEboyQHpj8C1vF","rect":[400,0,100,100],"offset":[0,0],"originalSize":[100,100],"capInsets":[0,0,0,0]}},{"__type__":"cc.SpriteFrame","content":{"name":"284","texture":"0fAmK8znJEboyQHpj8C1vF","rect":[600,900,100,100],"offset":[0,0],"originalSize":[100,100],"capInsets":[0,0,0,0]}},{"__type__":"cc.SpriteFrame","content":{"name":"1893","texture":"0fAmK8znJEboyQHpj8C1vF","rect":[300,200,100,100],"offset":[0,0],"originalSize":[100,100],"capInsets":[0,0,0,0]}},{"__type__":"cc.SpriteFrame","content":{"name":"280","texture":"0fAmK8znJEboyQHpj8C1vF","rect":[900,500,100,100],"offset":[0,0],"originalSize":[100,100],"capInsets":[0,0,0,0]}},{"__type__":"cc.SpriteFrame","content":{"name":"1912","texture":"0fAmK8znJEboyQHpj8C1vF","rect":[900,300,100,100],"offset":[0,0],"originalSize":[100,100],"capInsets":[0,0,0,0]}},{"__type__":"cc.SpriteFrame","content":{"name":"1926","texture":"0fAmK8znJEboyQHpj8C1vF","rect":[500,400,100,100],"offset":[0,0],"originalSize":[100,100],"capInsets":[0,0,0,0]}},{"__type__":"cc.SpriteFrame","content":{"name":"287","texture":"0fAmK8znJEboyQHpj8C1vF","rect":[800,600,100,100],"offset":[0,0],"originalSize":[100,100],"capInsets":[0,0,0,0]}},{"__type__":"cc.SpriteFrame","content":{"name":"2215","texture":"0fAmK8znJEboyQHpj8C1vF","rect":[500,800,100,100],"offset":[0,0],"originalSize":[100,100],"capInsets":[0,0,0,0]}},{"__type__":"cc.SpriteFrame","content":{"name":"1160","texture":"0fAmK8znJEboyQHpj8C1vF","rect":[300,0,100,100],"offset":[0,0],"originalSize":[100,100],"capInsets":[0,0,0,0]}},{"__type__":"cc.SpriteFrame","content":{"name":"1488","texture":"0fAmK8znJEboyQHpj8C1vF","rect":[200,100,100,100],"offset":[0,0],"originalSize":[100,100],"capInsets":[0,0,0,0]}},{"__type__":"cc.SpriteFrame","content":{"name":"1920","texture":"0fAmK8znJEboyQHpj8C1vF","rect":[400,700,100,100],"offset":[0,0],"originalSize":[100,100],"capInsets":[0,0,0,0]}},{"__type__":"cc.SpriteFrame","content":{"name":"1919","texture":"0fAmK8znJEboyQHpj8C1vF","rect":[400,600,100,100],"offset":[0,0],"originalSize":[100,100],"capInsets":[0,0,0,0]}},{"__type__":"cc.SpriteFrame","content":{"name":"2195","texture":"0fAmK8znJEboyQHpj8C1vF","rect":[500,700,100,100],"offset":[0,0],"originalSize":[100,100],"capInsets":[0,0,0,0]}},{"__type__":"cc.SpriteFrame","content":{"name":"1257","texture":"0fAmK8znJEboyQHpj8C1vF","rect":[900,0,100,100],"offset":[0,0],"originalSize":[100,100],"capInsets":[0,0,0,0]}},{"__type__":"cc.SpriteFrame","content":{"name":"1894","texture":"0fAmK8znJEboyQHpj8C1vF","rect":[400,200,100,100],"offset":[0,0],"originalSize":[100,100],"capInsets":[0,0,0,0]}},{"__type__":"cc.SpriteFrame","content":{"name":"1359","texture":"0fAmK8znJEboyQHpj8C1vF","rect":[100,700,100,100],"offset":[0,0],"originalSize":[100,100],"capInsets":[0,0,0,0]}},{"__type__":"cc.SpriteFrame","content":{"name":"1902","texture":"0fAmK8znJEboyQHpj8C1vF","rect":[300,500,100,100],"offset":[0,0],"originalSize":[100,100],"capInsets":[0,0,0,0]}},{"__type__":"cc.SpriteFrame","content":{"name":"1898","texture":"0fAmK8znJEboyQHpj8C1vF","rect":[800,200,100,100],"offset":[0,0],"originalSize":[100,100],"capInsets":[0,0,0,0]}},{"__type__":"cc.SpriteFrame","content":{"name":"855","texture":"0fAmK8znJEboyQHpj8C1vF","rect":[900,800,100,100],"offset":[0,0],"originalSize":[100,100],"capInsets":[0,0,0,0]}},{"__type__":"cc.SpriteFrame","content":{"name":"294","texture":"0fAmK8znJEboyQHpj8C1vF","rect":[900,700,100,100],"offset":[0,0],"originalSize":[100,100],"capInsets":[0,0,0,0]}},{"__type__":"cc.SpriteFrame","content":{"name":"1907","texture":"0fAmK8znJEboyQHpj8C1vF","rect":[400,300,100,100],"offset":[0,0],"originalSize":[100,100],"capInsets":[0,0,0,0]}},{"__type__":"cc.SpriteFrame","content":{"name":"282","texture":"0fAmK8znJEboyQHpj8C1vF","rect":[600,700,100,100],"offset":[0,0],"originalSize":[100,100],"capInsets":[0,0,0,0]}},{"__type__":"cc.SpriteFrame","content":{"name":"1910","texture":"0fAmK8znJEboyQHpj8C1vF","rect":[700,300,100,100],"offset":[0,0],"originalSize":[100,100],"capInsets":[0,0,0,0]}},{"__type__":"cc.SpriteFrame","content":{"name":"1905","texture":"0fAmK8znJEboyQHpj8C1vF","rect":[300,800,100,100],"offset":[0,0],"originalSize":[100,100],"capInsets":[0,0,0,0]}},{"__type__":"cc.SpriteFrame","content":{"name":"1360","texture":"0fAmK8znJEboyQHpj8C1vF","rect":[100,800,100,100],"offset":[0,0],"originalSize":[100,100],"capInsets":[0,0,0,0]}},{"__type__":"cc.SpriteFrame","content":{"name":"1162","texture":"0fAmK8znJEboyQHpj8C1vF","rect":[500,0,100,100],"offset":[0,0],"originalSize":[100,100],"capInsets":[0,0,0,0]}},{"__type__":"cc.SpriteFrame","content":{"name":"1265","texture":"0fAmK8znJEboyQHpj8C1vF","rect":[100,100,100,100],"offset":[0,0],"originalSize":[100,100],"capInsets":[0,0,0,0]}},{"__type__":"cc.SpriteFrame","content":{"name":"1155","texture":"0fAmK8znJEboyQHpj8C1vF","rect":[0,700,100,100],"offset":[0,0],"originalSize":[100,100],"capInsets":[0,0,0,0]}},{"__type__":"cc.SpriteFrame","content":{"name":"1892","texture":"0fAmK8znJEboyQHpj8C1vF","rect":[200,900,100,100],"offset":[0,0],"originalSize":[100,100],"capInsets":[0,0,0,0]}},{"__type__":"cc.SpriteFrame","content":{"name":"915","texture":"0fAmK8znJEboyQHpj8C1vF","rect":[900,900,100,100],"offset":[0,0],"originalSize":[100,100],"capInsets":[0,0,0,0]}},{"__type__":"cc.SpriteFrame","content":{"name":"1561","texture":"0fAmK8znJEboyQHpj8C1vF","rect":[500,100,100,100],"offset":[0,0],"originalSize":[100,100],"capInsets":[0,0,0,0]}},{"__type__":"cc.SpriteFrame","content":{"name":"1157","texture":"0fAmK8znJEboyQHpj8C1vF","rect":[0,900,100,100],"offset":[0,0],"originalSize":[100,100],"capInsets":[0,0,0,0]}},{"__type__":"cc.SpriteFrame","content":{"name":"1914","texture":"0fAmK8znJEboyQHpj8C1vF","rect":[400,400,100,100],"offset":[0,0],"originalSize":[100,100],"capInsets":[0,0,0,0]}},{"__type__":"cc.SpriteFrame","content":{"name":"1243","texture":"0fAmK8znJEboyQHpj8C1vF","rect":[700,0,100,100],"offset":[0,0],"originalSize":[100,100],"capInsets":[0,0,0,0]}},{"__type__":"cc.SpriteFrame","content":{"name":"1906","texture":"0fAmK8znJEboyQHpj8C1vF","rect":[300,900,100,100],"offset":[0,0],"originalSize":[100,100],"capInsets":[0,0,0,0]}},{"__type__":"cc.SpriteFrame","content":{"name":"1909","texture":"0fAmK8znJEboyQHpj8C1vF","rect":[600,300,100,100],"offset":[0,0],"originalSize":[100,100],"capInsets":[0,0,0,0]}},{"__type__":"cc.SpriteFrame","content":{"name":"1153","texture":"0fAmK8znJEboyQHpj8C1vF","rect":[0,500,100,100],"offset":[0,0],"originalSize":[100,100],"capInsets":[0,0,0,0]}},{"__type__":"cc.SpriteAtlas","_name":"hair_end1.plist","_spriteFrames":{"277":{"__uuid__":"fbJagasbpKCpcXFAIufpqI"},"278":{"__uuid__":"35tzjvkDBBYrr2n9RlfEs4"},"279":{"__uuid__":"bdBy8dkplDRJm4zXl7BWbz"},"280":{"__uuid__":"3aryrbMWVOOIdQw/OaMzRL"},"281":{"__uuid__":"a98C5O2SVIOoMhvmiQRaS2"},"282":{"__uuid__":"6eZZF2lMBK2oD4cHnNSoCn"},"283":{"__uuid__":"dcvLc1Q9xFnYzktJlTKZ8O"},"284":{"__uuid__":"36x/+fSIBAu5pOJC/5UbVh"},"285":{"__uuid__":"dfvWLNwaRLj5VwkNcsJ0si"},"287":{"__uuid__":"44KbiyawZGdbW4CN3wGZ9w"},"288":{"__uuid__":"04y1Jvy7tL5LQ61wGNUDxF"},"289":{"__uuid__":"d7VxIn+rNC17WaEgF7hJG0"},"291":{"__uuid__":"ba47JgQe5O8KSInP3aueOB"},"292":{"__uuid__":"b6h9/IUHdHPZkcJbpWbIif"},"293":{"__uuid__":"e2Uol+M+pPppwmO+9T40ml"},"294":{"__uuid__":"6bepLns+dEiqcrycp8j+6+"},"295":{"__uuid__":"19Mt0Vn5VLdKp7CA/edoqf"},"296":{"__uuid__":"05yDXRqytP+Jfb2qy9YaJq"},"855":{"__uuid__":"64ALF/AtVCjIBzi+Cs3x+Y"},"915":{"__uuid__":"85o6ij2AJMV60oEMalfhm1"},"1028":{"__uuid__":"26g6eumwJBpoK4773UUAhx"},"1029":{"__uuid__":"28cnzaApBNt6enXQ7j9yr9"},"1062":{"__uuid__":"11hvw4B1tMdp04vRbE4a2G"},"1151":{"__uuid__":"aaeSM47RZM96u3i0gjfmWL"},"1152":{"__uuid__":"a606lp/xNI5JS5fB49WJ3C"},"1153":{"__uuid__":"9dbxbfYNtIdII9Lubl48jP"},"1154":{"__uuid__":"037I0g9WBIrK9T+BFN+kGa"},"1155":{"__uuid__":"81bI+kze5L9qMZyCnRPo0a"},"1156":{"__uuid__":"15JcX75oRO95LhVDbEIk6f"},"1157":{"__uuid__":"8dHuqQa4lGarB6uE/AYYBu"},"1158":{"__uuid__":"0bLAko90tJMJsE2hm9ubN2"},"1159":{"__uuid__":"2bik6LJblHiL4AgowhYBFr"},"1160":{"__uuid__":"4at01lYlRMlKBlUwZuoyBd"},"1161":{"__uuid__":"36wjSzrj9MVol6MNpobxIe"},"1162":{"__uuid__":"7dqQwUTnZKJaPTNJcZyM4w"},"1163":{"__uuid__":"ed87lI5htO/rSDr0rvMwxJ"},"1243":{"__uuid__":"91t0P1X7RCqo0P/ONGzrcX"},"1252":{"__uuid__":"ceBcD4t3dASLd82mDR5S4X"},"1257":{"__uuid__":"5eoaFYwCpM1q/yBWN0fRw9"},"1265":{"__uuid__":"7dvcg/dBZLRYUHUmRUb8q8"},"1276":{"__uuid__":"bbV7NJJ/1PoYxfXeQ4AjBF"},"1287":{"__uuid__":"eeW/jVClVIBpkBd9Mv5Uib"},"1292":{"__uuid__":"f1g2XDTdxO05jPoYavdIdp"},"1329":{"__uuid__":"c8KbTbDilGfb4WQ8oUxTFf"},"1340":{"__uuid__":"b7AZGRtfVBEoRX0YAIwiM7"},"1359":{"__uuid__":"618YGSBN9FRawU5fjvpeBP"},"1360":{"__uuid__":"7bTE6SxjdMkJZ1rzihQh1/"},"1366":{"__uuid__":"0dORJ1FJZL15HyD0hW6Ywe"},"1488":{"__uuid__":"539TSWDYtMZIqsXTmjk6Hx"},"1508":{"__uuid__":"1dSYnOMUZNjIy3MGpviduk"},"1544":{"__uuid__":"e7g2N3fSpLCLjPi3/eD0Vd"},"1561":{"__uuid__":"8bOsEZappCvJTdPc2TXJe1"},"1571":{"__uuid__":"2arQ0Ah0hGDJScHtk3hUVL"},"1586":{"__uuid__":"a8alvnb85Hr4uMCw9Pryko"},"1650":{"__uuid__":"d0lI+9g9NEiYmZLdmMzZ13"},"1659":{"__uuid__":"f5bGbP3NFNVZ9KINgmGV4K"},"1671":{"__uuid__":"eeONaZ1Q1Jd5yXXKa5zxYk"},"1726":{"__uuid__":"aa6UMdcFVGrqC28A08ccnL"},"1737":{"__uuid__":"aaGeK0SSFAfqdzVRzAK32S"},"1738":{"__uuid__":"2eferRac1J5phhFAE5vHP0"},"1739":{"__uuid__":"f8D/583X5Eqo26XAhe09E0"},"1785":{"__uuid__":"14nWgN6olK05KQ6uSiY1sm"},"1891":{"__uuid__":"1aZkG5RhBF9IIQqFUCnEwC"},"1892":{"__uuid__":"81c61WXihBaq4mSWlngloR"},"1893":{"__uuid__":"37sUqCuYJC6Kplf65SK74B"},"1894":{"__uuid__":"61TFnqERJJCY8n4zvnc+h6"},"1895":{"__uuid__":"04WOyakfNPwodINC5jDf4q"},"1896":{"__uuid__":"bfvyYiwR9F2aBdDU5xaQgK"},"1897":{"__uuid__":"e9IuOdmNxOsZHb/8+GoKQh"},"1898":{"__uuid__":"62ipHl2SVOC47XNQxeB6Zj"},"1899":{"__uuid__":"c1gqWt3jNNdpFAOMqFJAHN"},"1900":{"__uuid__":"f3Wm7zeoZK6ZMHMozWc7T1"},"1901":{"__uuid__":"1bWO1MATZIloF0dX6MIQ0C"},"1902":{"__uuid__":"61/ZZVQOtJSpg8FIl4II1Y"},"1903":{"__uuid__":"dcICf8hURMNbEQfOVheorw"},"1904":{"__uuid__":"f9rmaWAFpB34Xlo1phwL/N"},"1905":{"__uuid__":"7aB8S+vGVIe5z1EwUDJssb"},"1906":{"__uuid__":"92zbEs9B1GM74VziAWCVA8"},"1907":{"__uuid__":"6eOSI9GeRAqIgbSkWPLfCg"},"1908":{"__uuid__":"e3vkZVSa1H7Ltx49WHABGJ"},"1909":{"__uuid__":"9dWlrU7qpGNLyRojKV91in"},"1910":{"__uuid__":"7835iLqEhCKbIfdmCUGO2E"},"1911":{"__uuid__":"e8CZ1OFMRKxr+5agNdXXyA"},"1912":{"__uuid__":"3b3S3x2g5JCIV6Nq+8IAqN"},"1914":{"__uuid__":"8ebR01/JVMb6OSxsIKugXU"},"1916":{"__uuid__":"31LKirWjVEpYmsyiDCt1N/"},"1919":{"__uuid__":"59Af2BFIRADLRzqJcG306j"},"1920":{"__uuid__":"58nuNxY7NE9b0sqdXW9rOF"},"1922":{"__uuid__":"05mUdywHZNraxCD03uwE2b"},"1924":{"__uuid__":"faipqcsD9PUawLpv+vnFKG"},"1926":{"__uuid__":"40B35hcm9PXZm5hrQZK6U5"},"1928":{"__uuid__":"e3ccInPJ5DFI5I3iRukZgB"},"1937":{"__uuid__":"a8gFgQa91Iy4WgGwvoQpVv"},"1980":{"__uuid__":"f4vIyWfkFMlL02nkz2w8Pc"},"2009":{"__uuid__":"c1O63GgLpG077AfOJ/vmXd"},"2038":{"__uuid__":"dawOhZ061CNYBQ/3XdBE3O"},"2171":{"__uuid__":"c4i2rgkRZDvrUz9cNnvFGY"},"2195":{"__uuid__":"59+4Ms59VGSaWXYBnz/2VQ"},"2215":{"__uuid__":"466AsspOhOuoeo8rF7sRz2"},"2220":{"__uuid__":"1736CIBupNoK3Ey4Et6Nie"}}},{"__type__":"cc.SpriteFrame","content":{"name":"1152","texture":"0fAmK8znJEboyQHpj8C1vF","rect":[0,400,100,100],"offset":[0,0],"originalSize":[100,100],"capInsets":[0,0,0,0]}},{"__type__":"cc.SpriteFrame","content":{"name":"1586","texture":"0fAmK8znJEboyQHpj8C1vF","rect":[700,100,100,100],"offset":[0,0],"originalSize":[100,100],"capInsets":[0,0,0,0]}},{"__type__":"cc.SpriteFrame","content":{"name":"1937","texture":"0fAmK8znJEboyQHpj8C1vF","rect":[700,400,100,100],"offset":[0,0],"originalSize":[100,100],"capInsets":[0,0,0,0]}},{"__type__":"cc.SpriteFrame","content":{"name":"281","texture":"0fAmK8znJEboyQHpj8C1vF","rect":[600,600,100,100],"offset":[0,0],"originalSize":[100,100],"capInsets":[0,0,0,0]}},{"__type__":"cc.SpriteFrame","content":{"name":"1737","texture":"0fAmK8znJEboyQHpj8C1vF","rect":[200,400,100,100],"offset":[0,0],"originalSize":[100,100],"capInsets":[0,0,0,0]}},{"__type__":"cc.SpriteFrame","content":{"name":"1151","texture":"0fAmK8znJEboyQHpj8C1vF","rect":[0,300,100,100],"offset":[0,0],"originalSize":[100,100],"capInsets":[0,0,0,0]}},{"__type__":"cc.SpriteFrame","content":{"name":"1726","texture":"0fAmK8znJEboyQHpj8C1vF","rect":[200,300,100,100],"offset":[0,0],"originalSize":[100,100],"capInsets":[0,0,0,0]}},{"__type__":"cc.SpriteFrame","content":{"name":"292","texture":"0fAmK8znJEboyQHpj8C1vF","rect":[700,900,100,100],"offset":[0,0],"originalSize":[100,100],"capInsets":[0,0,0,0]}},{"__type__":"cc.SpriteFrame","content":{"name":"1340","texture":"0fAmK8znJEboyQHpj8C1vF","rect":[100,600,100,100],"offset":[0,0],"originalSize":[100,100],"capInsets":[0,0,0,0]}},{"__type__":"cc.SpriteFrame","content":{"name":"291","texture":"0fAmK8znJEboyQHpj8C1vF","rect":[700,800,100,100],"offset":[0,0],"originalSize":[100,100],"capInsets":[0,0,0,0]}},{"__type__":"cc.SpriteFrame","content":{"name":"1276","texture":"0fAmK8znJEboyQHpj8C1vF","rect":[100,200,100,100],"offset":[0,0],"originalSize":[100,100],"capInsets":[0,0,0,0]}},{"__type__":"cc.SpriteFrame","content":{"name":"279","texture":"0fAmK8znJEboyQHpj8C1vF","rect":[800,500,100,100],"offset":[0,0],"originalSize":[100,100],"capInsets":[0,0,0,0]}},{"__type__":"cc.SpriteFrame","content":{"name":"1896","texture":"0fAmK8znJEboyQHpj8C1vF","rect":[600,200,100,100],"offset":[0,0],"originalSize":[100,100],"capInsets":[0,0,0,0]}},{"__type__":"cc.SpriteFrame","content":{"name":"2009","texture":"0fAmK8znJEboyQHpj8C1vF","rect":[900,400,100,100],"offset":[0,0],"originalSize":[100,100],"capInsets":[0,0,0,0]}},{"__type__":"cc.SpriteFrame","content":{"name":"1899","texture":"0fAmK8znJEboyQHpj8C1vF","rect":[900,200,100,100],"offset":[0,0],"originalSize":[100,100],"capInsets":[0,0,0,0]}},{"__type__":"cc.SpriteFrame","content":{"name":"2171","texture":"0fAmK8znJEboyQHpj8C1vF","rect":[500,600,100,100],"offset":[0,0],"originalSize":[100,100],"capInsets":[0,0,0,0]}},{"__type__":"cc.SpriteFrame","content":{"name":"1329","texture":"0fAmK8znJEboyQHpj8C1vF","rect":[100,500,100,100],"offset":[0,0],"originalSize":[100,100],"capInsets":[0,0,0,0]}},{"__type__":"cc.SpriteFrame","content":{"name":"1252","texture":"0fAmK8znJEboyQHpj8C1vF","rect":[800,0,100,100],"offset":[0,0],"originalSize":[100,100],"capInsets":[0,0,0,0]}},{"__type__":"cc.SpriteFrame","content":{"name":"1650","texture":"0fAmK8znJEboyQHpj8C1vF","rect":[800,100,100,100],"offset":[0,0],"originalSize":[100,100],"capInsets":[0,0,0,0]}},{"__type__":"cc.SpriteFrame","content":{"name":"289","texture":"0fAmK8znJEboyQHpj8C1vF","rect":[700,700,100,100],"offset":[0,0],"originalSize":[100,100],"capInsets":[0,0,0,0]}},{"__type__":"cc.SpriteFrame","content":{"name":"2038","texture":"0fAmK8znJEboyQHpj8C1vF","rect":[500,500,100,100],"offset":[0,0],"originalSize":[100,100],"capInsets":[0,0,0,0]}},{"__type__":"cc.SpriteFrame","content":{"name":"1903","texture":"0fAmK8znJEboyQHpj8C1vF","rect":[300,600,100,100],"offset":[0,0],"originalSize":[100,100],"capInsets":[0,0,0,0]}},{"__type__":"cc.SpriteFrame","content":{"name":"283","texture":"0fAmK8znJEboyQHpj8C1vF","rect":[600,800,100,100],"offset":[0,0],"originalSize":[100,100],"capInsets":[0,0,0,0]}},{"__type__":"cc.SpriteFrame","content":{"name":"285","texture":"0fAmK8znJEboyQHpj8C1vF","rect":[700,600,100,100],"offset":[0,0],"originalSize":[100,100],"capInsets":[0,0,0,0]}},{"__type__":"cc.SpriteFrame","content":{"name":"293","texture":"0fAmK8znJEboyQHpj8C1vF","rect":[800,700,100,100],"offset":[0,0],"originalSize":[100,100],"capInsets":[0,0,0,0]}},{"__type__":"cc.SpriteFrame","content":{"name":"1928","texture":"0fAmK8znJEboyQHpj8C1vF","rect":[600,400,100,100],"offset":[0,0],"originalSize":[100,100],"capInsets":[0,0,0,0]}},{"__type__":"cc.SpriteFrame","content":{"name":"1908","texture":"0fAmK8znJEboyQHpj8C1vF","rect":[500,300,100,100],"offset":[0,0],"originalSize":[100,100],"capInsets":[0,0,0,0]}},{"__type__":"cc.SpriteFrame","content":{"name":"1544","texture":"0fAmK8znJEboyQHpj8C1vF","rect":[400,100,100,100],"offset":[0,0],"originalSize":[100,100],"capInsets":[0,0,0,0]}},{"__type__":"cc.SpriteFrame","content":{"name":"1911","texture":"0fAmK8znJEboyQHpj8C1vF","rect":[800,300,100,100],"offset":[0,0],"originalSize":[100,100],"capInsets":[0,0,0,0]}},{"__type__":"cc.SpriteFrame","content":{"name":"1897","texture":"0fAmK8znJEboyQHpj8C1vF","rect":[700,200,100,100],"offset":[0,0],"originalSize":[100,100],"capInsets":[0,0,0,0]}},{"__type__":"cc.SpriteFrame","content":{"name":"1163","texture":"0fAmK8znJEboyQHpj8C1vF","rect":[600,0,100,100],"offset":[0,0],"originalSize":[100,100],"capInsets":[0,0,0,0]}},{"__type__":"cc.SpriteFrame","content":{"name":"1671","texture":"0fAmK8znJEboyQHpj8C1vF","rect":[200,200,100,100],"offset":[0,0],"originalSize":[100,100],"capInsets":[0,0,0,0]}},{"__type__":"cc.SpriteFrame","content":{"name":"1287","texture":"0fAmK8znJEboyQHpj8C1vF","rect":[100,300,100,100],"offset":[0,0],"originalSize":[100,100],"capInsets":[0,0,0,0]}},{"__type__":"cc.SpriteFrame","content":{"name":"1292","texture":"0fAmK8znJEboyQHpj8C1vF","rect":[100,400,100,100],"offset":[0,0],"originalSize":[100,100],"capInsets":[0,0,0,0]}},{"__type__":"cc.SpriteFrame","content":{"name":"1900","texture":"0fAmK8znJEboyQHpj8C1vF","rect":[300,300,100,100],"offset":[0,0],"originalSize":[100,100],"capInsets":[0,0,0,0]}},{"__type__":"cc.SpriteFrame","content":{"name":"1980","texture":"0fAmK8znJEboyQHpj8C1vF","rect":[800,400,100,100],"offset":[0,0],"originalSize":[100,100],"capInsets":[0,0,0,0]}},{"__type__":"cc.SpriteFrame","content":{"name":"1659","texture":"0fAmK8znJEboyQHpj8C1vF","rect":[900,100,100,100],"offset":[0,0],"originalSize":[100,100],"capInsets":[0,0,0,0]}},{"__type__":"cc.SpriteFrame","content":{"name":"1739","texture":"0fAmK8znJEboyQHpj8C1vF","rect":[200,600,100,100],"offset":[0,0],"originalSize":[100,100],"capInsets":[0,0,0,0]}},{"__type__":"cc.SpriteFrame","content":{"name":"1904","texture":"0fAmK8znJEboyQHpj8C1vF","rect":[300,700,100,100],"offset":[0,0],"originalSize":[100,100],"capInsets":[0,0,0,0]}},{"__type__":"cc.SpriteFrame","content":{"name":"1924","texture":"0fAmK8znJEboyQHpj8C1vF","rect":[400,900,100,100],"offset":[0,0],"originalSize":[100,100],"capInsets":[0,0,0,0]}},{"__type__":"cc.SpriteFrame","content":{"name":"277","texture":"0fAmK8znJEboyQHpj8C1vF","rect":[600,500,100,100],"offset":[0,0],"originalSize":[100,100],"capInsets":[0,0,0,0]}}]